global cPuzzleTotal, cSavePuzzleTotal, cInterface, mouseChunk, lastMouseX, lastMouseY, keyChunk, menuName, titleName, menuStat, CR, QU, rectTotal, r1, r2, r3, R4, token1, token2, token3, zipCode, currGame, lastPuzzle, currPuzzle, nextPuzzle, directToScreenHelp, chunkMenuStat, chunkMenuName, loadPuzzleCount, startTicks, currRollOver, lastRollOver, currMenuDisplay, cSwords1, cSwords2, cWands1, cWands2, cCups1, cCups2, cPentacles1, cPentacles2, cMansion1, cMansion2, cPrologue, cPreHP, cEndHP, cHighPriestess, cSevenCups, cMoonMorph, cMoonsMap, cMoonsPuzzles, cGameMenus, cTokens, cPreFinale, cFinale, cActiveSN, cScrollSN, cHelpSN, cMenuSN, cForwardSN, cReverseSN, cMoneySN, cTarotTotal, cNewGameNum, cOpenGameNum, cRevGameNum, cFileTotal, cTarot1, cTarot2, cTarot3, cTarot4, cTarot5, cHelpTokens, cMenuPuzzles, cInitFreeBytes, cInitMemorySize, cTarotCards, cTypeCurrPuzzle, cGameDirectory, cWork, cLink, cXtraDirectory, cFileIO, tName, fName, fData, pNum, pStat, pData, pDone, pPage, pHelp, pMenu, pVolume, pFrame, pWindowCode, pWordStat63, prefNumber, prefTotal, prefChunk, pSwords, pWands, pCups, pPentacles, pTotalSwords, pTotalWands, pTotalCups, pTotalPentacles, theDataStatus, pFin_Count, pFin_Incre, pFin_Total, pClickToContinue, snd_Channel_Array, snd_Channel_Count, _Save_Stat, _Save_Type, c_Interface_Mode, c_Interface_MouseDown, c_Interface_DoubleClick, c_Interface_KeyDown, activity_Array, activity_Count, activity_Total, activity_Launch, playMode, pmZero, pmPlay, pmHelp, pmClick, pmSave, pmDeActivate, pmActivate, pz_Available, pz_Total, pz_LastLaunch, menu_Key, menuClick_Array, menuClick_Count, theDirectorVersion, createNewGameData, csGrid, csJumble, csClickCode, csPhrase, csConcat, csLetterSlide, csPatchPirate, csPatchStamp, csMorphText, csHerb, csTracer, csInventory, csSeven, csAuction, csWager, csTarot, csWagerTarot, csPentacle, csPreFinale, csMorph, csCoins, csHalves, csFillin, csPatchSlider, csMansion, csDEL, csHEX, csREM, csCON, totalName, cSavedGamesDirectory, cSaveDirectoryCliff, status_Quit_The_Game, status_First_Launch

on init_StartGame
  [  0] pushzero ................................ <0>
  [  1] setglobal 191 ........................... createNewGameData = 0
  [  3] pushint8 1 .............................. <1>
  [  5] setglobal 382 ........................... status_First_Launch = 1
  [  8] gettoplevelprop 638 ..................... <_sound>
  [ 11] pushzero ................................ <0>
  [ 12] setobjprop 639 .......................... _sound.soundKeepDevice = 0
  [ 15] gettoplevelprop 638 ..................... <_sound>
  [ 18] pushzero ................................ <0>
  [ 19] setobjprop 640 .......................... _sound.soundMixMedia = 0
  [ 22] pusharglist 0 ........................... <>
  [ 24] thebuiltin 641 .......................... <the memorysize>
  [ 27] pushint16 1024 .......................... <1024>
  [ 30] div ..................................... <the memorysize / 1024>
  [ 31] pusharglist 1 ........................... <the memorysize / 1024>
  [ 33] extcall 42 .............................. <integer(the memorysize / 1024)>
  [ 35] setglobal 487 ........................... cInitMemorySize = integer(the memorysize / 1024)
  [ 38] pusharglist 0 ........................... <>
  [ 40] thebuiltin 642 .......................... <the freeBytes>
  [ 43] pushint16 1024 .......................... <1024>
  [ 46] div ..................................... <the freeBytes / 1024>
  [ 47] pusharglist 1 ........................... <the freeBytes / 1024>
  [ 49] extcall 42 .............................. <integer(the freeBytes / 1024)>
  [ 51] setglobal 488 ........................... cInitFreeBytes = integer(the freeBytes / 1024)
  [ 54] pushint8 1 .............................. <1>
  [ 56] setlocal 0 .............................. activeState = 1
  [ 58] pushzero ................................ <0>
  [ 59] setlocal 1 .............................. activeStatePuzzle = 0
  [ 61] pusharglistnoret 0 ...................... <>
  [ 63] extcall 251 ............................. noInterface()
  [ 65] pushzero ................................ <0>
  [ 66] setglobal 80 ............................ c_Interface_Mode = 0
  [ 68] pushzero ................................ <0>
  [ 69] setglobal 503 ........................... cTypeCurrPuzzle = 0
  [ 72] pushzero ................................ <0>
  [ 73] setglobal 565 ........................... c_Interface_MouseDown = 0
  [ 76] pushzero ................................ <0>
  [ 77] setglobal 89 ............................ c_Interface_KeyDown = 0
  [ 79] pushzero ................................ <0>
  [ 80] setglobal 476 ........................... c_Interface_DoubleClick = 0
  [ 83] pusharglistnoret 0 ...................... <>
  [ 85] extcall 415 ............................. zero_DoubleClick()
  [ 88] pushint8 12 ............................. <12>
  [ 90] setglobal 181 ........................... cTarotTotal = 12
  [ 92] pushint8 13 ............................. <13>
  [ 94] setglobal 179 ........................... cNewGameNum = 13
  [ 96] pushint8 14 ............................. <14>
  [ 98] setglobal 171 ........................... cRevGameNum = 14
  [100] pushint8 15 ............................. <15>
  [102] setglobal 161 ........................... cOpenGameNum = 15
  [104] pushint8 15 ............................. <15>
  [106] setglobal 195 ........................... cFileTotal = 15
  [108] pushint8 77 ............................. <77>
  [110] setglobal 366 ........................... cMenuPuzzles = 77
  [113] pushint16 128 ........................... <128>
  [116] setglobal 262 ........................... cPuzzleTotal = 128
  [119] pushint8 100 ............................ <100>
  [121] setglobal 203 ........................... cSavePuzzleTotal = 100
  [123] pushint8 1 .............................. <1>
  [125] setglobal 248 ........................... cPrologue = 1
  [127] pushint8 2 .............................. <2>
  [129] setglobal 282 ........................... cSwords1 = 2
  [132] pushint8 3 .............................. <3>
  [134] setglobal 329 ........................... cMoonMorph = 3
  [137] pushint8 18 ............................. <18>
  [139] setglobal 286 ........................... cSwords2 = 18
  [142] pushint8 19 ............................. <19>
  [144] setglobal 284 ........................... cWands1 = 19
  [147] pushint8 37 ............................. <37>
  [149] setglobal 297 ........................... cWands2 = 37
  [152] pushint8 38 ............................. <38>
  [154] setglobal 298 ........................... cCups1 = 38
  [157] pushint8 55 ............................. <55>
  [159] setglobal 299 ........................... cCups2 = 55
  [162] pushint8 56 ............................. <56>
  [164] setglobal 300 ........................... cPentacles1 = 56
  [167] pushint8 71 ............................. <71>
  [169] setglobal 283 ........................... cPentacles2 = 71
  [172] pushint8 72 ............................. <72>
  [174] setglobal 98 ............................ cPreFinale = 72
  [176] pushint8 73 ............................. <73>
  [178] setglobal 287 ........................... cMansion1 = 73
  [181] pushint8 79 ............................. <79>
  [183] setglobal 288 ........................... cMansion2 = 79
  [186] pushint8 80 ............................. <80>
  [188] setglobal 25 ............................ cFinale = 80
  [190] pushint8 87 ............................. <87>
  [192] setglobal 247 ........................... cHelpTokens = 87
  [194] pushint8 88 ............................. <88>
  [196] setglobal 264 ........................... cPreHP = 88
  [199] pushint8 89 ............................. <89>
  [201] setglobal 381 ........................... cEndHP = 89
  [204] pushint8 90 ............................. <90>
  [206] setglobal 261 ........................... cHighPriestess = 90
  [209] pushint8 91 ............................. <91>
  [211] setglobal 285 ........................... cSevenCups = 91
  [214] pushint8 92 ............................. <92>
  [216] setglobal 643 ........................... cTarot1 = 92
  [219] pushint8 93 ............................. <93>
  [221] setglobal 644 ........................... cTarot2 = 93
  [224] pushint8 94 ............................. <94>
  [226] setglobal 645 ........................... cTarot3 = 94
  [229] pushint8 95 ............................. <95>
  [231] setglobal 646 ........................... cTarot4 = 95
  [234] pushint8 96 ............................. <96>
  [236] setglobal 647 ........................... cTarot5 = 96
  [239] pushint8 97 ............................. <97>
  [241] setglobal 290 ........................... cMoonsMap = 97
  [244] pushint8 98 ............................. <98>
  [246] setglobal 291 ........................... cMoonsPuzzles = 98
  [249] pushint8 99 ............................. <99>
  [251] setglobal 21 ............................ cGameMenus = 99
  [253] pushint8 100 ............................ <100>
  [255] setglobal 202 ........................... cTokens = 100
  [257] pushint8 1 .............................. <1>
  [259] setglobal 48 ............................ cActiveSN = 1
  [261] pushint8 3 .............................. <3>
  [263] setglobal 57 ............................ cScrollSN = 3
  [265] pushint8 4 .............................. <4>
  [267] setglobal 265 ........................... cHelpSN = 4
  [270] pushint8 5 .............................. <5>
  [272] setglobal 60 ............................ cMenuSN = 5
  [274] pushint8 6 .............................. <6>
  [276] setglobal 58 ............................ cForwardSN = 6
  [278] pushint8 7 .............................. <7>
  [280] setglobal 59 ............................ cReverseSN = 7
  [282] pushint8 8 .............................. <8>
  [284] setglobal 601 ........................... cMoneySN = 8
  [287] getglobal 57 ............................ <cScrollSN>
  [289] pusharglistnoret 1 ...................... <cScrollSN>
  [291] extcall 413 ............................. _Set_DirectorInControl(cScrollSN)
  [294] getglobal 265 ........................... <cHelpSN>
  [297] pusharglistnoret 1 ...................... <cHelpSN>
  [299] extcall 413 ............................. _Set_DirectorInControl(cHelpSN)
  [302] pushint8 13 ............................. <13>
  [304] pusharglist 1 ........................... <13>
  [306] extcall 611 ............................. <numToChar(13)>
  [309] setglobal 263 ........................... CR = numToChar(13)
  [312] pushint8 34 ............................. <34>
  [314] pusharglist 1 ........................... <34>
  [316] extcall 611 ............................. <numToChar(34)>
  [319] setglobal 486 ........................... QU = numToChar(34)
  [322] pusharglist 0 ........................... <>
  [324] extcall 313 ............................. <list()>
  [327] setglobal 178 ........................... tName = list()
  [329] pusharglist 0 ........................... <>
  [331] extcall 313 ............................. <list()>
  [334] setglobal 143 ........................... fName = list()
  [336] pusharglist 0 ........................... <>
  [338] extcall 313 ............................. <list()>
  [341] setglobal 155 ........................... fData = list()
  [343] pusharglist 0 ........................... <>
  [345] extcall 313 ............................. <list()>
  [348] setglobal 365 ........................... pNum = list()
  [351] pusharglist 0 ........................... <>
  [353] extcall 313 ............................. <list()>
  [356] setglobal 93 ............................ pStat = list()
  [358] pusharglist 0 ........................... <>
  [360] extcall 313 ............................. <list()>
  [363] setglobal 188 ........................... pData = list()
  [365] pusharglist 0 ........................... <>
  [367] extcall 313 ............................. <list()>
  [370] setglobal 189 ........................... pDone = list()
  [372] pusharglist 0 ........................... <>
  [374] extcall 313 ............................. <list()>
  [377] setglobal 100 ........................... pPage = list()
  [379] pusharglist 0 ........................... <>
  [381] extcall 313 ............................. <list()>
  [384] setglobal 101 ........................... pHelp = list()
  [386] pusharglist 0 ........................... <>
  [388] extcall 313 ............................. <list()>
  [391] setglobal 34 ............................ pMenu = list()
  [393] pusharglist 0 ........................... <>
  [395] extcall 313 ............................. <list()>
  [398] setglobal 330 ........................... pVolume = list()
  [401] pusharglist 0 ........................... <>
  [403] extcall 313 ............................. <list()>
  [406] setglobal 331 ........................... pFrame = list()
  [409] pusharglist 0 ........................... <>
  [411] extcall 313 ............................. <list()>
  [414] setglobal 183 ........................... pSwords = list()
  [416] pusharglist 0 ........................... <>
  [418] extcall 313 ............................. <list()>
  [421] setglobal 184 ........................... pWands = list()
  [423] pusharglist 0 ........................... <>
  [425] extcall 313 ............................. <list()>
  [428] setglobal 185 ........................... pCups = list()
  [430] pusharglist 0 ........................... <>
  [432] extcall 313 ............................. <list()>
  [435] setglobal 186 ........................... pPentacles = list()
  [437] pushzero ................................ <0>
  [438] setlocal 2 .............................. pVolumeOff = 0
  [440] pusharglist 0 ........................... <>
  [442] extcall 313 ............................. <list()>
  [445] setglobal 206 ........................... pWordStat63 = list()
  [447] pusharglistnoret 0 ...................... <>
  [449] extcall 192 ............................. initWordStat63()
  [451] pusharglist 0 ........................... <>
  [453] extcall 313 ............................. <list()>
  [456] setglobal 521 ........................... csMorph = list()
  [459] pusharglist 0 ........................... <>
  [461] extcall 313 ............................. <list()>
  [464] setglobal 522 ........................... csCoins = list()
  [467] pusharglist 0 ........................... <>
  [469] extcall 313 ............................. <list()>
  [472] setglobal 523 ........................... csHalves = list()
  [475] pusharglist 0 ........................... <>
  [477] extcall 313 ............................. <list()>
  [480] setglobal 349 ........................... csFillin = list()
  [483] pusharglist 0 ........................... <>
  [485] extcall 313 ............................. <list()>
  [488] setglobal 524 ........................... csPatchSlider = list()
  [491] pusharglist 0 ........................... <>
  [493] extcall 313 ............................. <list()>
  [496] setglobal 363 ........................... csGrid = list()
  [499] pusharglist 0 ........................... <>
  [501] extcall 313 ............................. <list()>
  [504] setglobal 362 ........................... csJumble = list()
  [507] pusharglist 0 ........................... <>
  [509] extcall 313 ............................. <list()>
  [512] setglobal 361 ........................... csClickCode = list()
  [515] pusharglist 0 ........................... <>
  [517] extcall 313 ............................. <list()>
  [520] setglobal 360 ........................... csPhrase = list()
  [523] pusharglist 0 ........................... <>
  [525] extcall 313 ............................. <list()>
  [528] setglobal 359 ........................... csConcat = list()
  [531] pusharglist 0 ........................... <>
  [533] extcall 313 ............................. <list()>
  [536] setglobal 358 ........................... csLetterSlide = list()
  [539] pusharglist 0 ........................... <>
  [541] extcall 313 ............................. <list()>
  [544] setglobal 289 ........................... csPatchPirate = list()
  [547] pusharglist 0 ........................... <>
  [549] extcall 313 ............................. <list()>
  [552] setglobal 357 ........................... csPatchStamp = list()
  [555] pusharglist 0 ........................... <>
  [557] extcall 313 ............................. <list()>
  [560] setglobal 356 ........................... csMorphText = list()
  [563] pusharglist 0 ........................... <>
  [565] extcall 313 ............................. <list()>
  [568] setglobal 355 ........................... csHerb = list()
  [571] pusharglist 0 ........................... <>
  [573] extcall 313 ............................. <list()>
  [576] setglobal 354 ........................... csTracer = list()
  [579] pusharglist 0 ........................... <>
  [581] extcall 313 ............................. <list()>
  [584] setglobal 350 ........................... csPentacle = list()
  [587] pusharglist 0 ........................... <>
  [589] extcall 313 ............................. <list()>
  [592] setglobal 353 ........................... csInventory = list()
  [595] pusharglist 0 ........................... <>
  [597] extcall 313 ............................. <list()>
  [600] setglobal 352 ........................... csSeven = list()
  [603] pusharglist 0 ........................... <>
  [605] extcall 313 ............................. <list()>
  [608] setglobal 351 ........................... csAuction = list()
  [611] pusharglist 0 ........................... <>
  [613] extcall 313 ............................. <list()>
  [616] setglobal 217 ........................... csWager = list()
  [618] pusharglist 0 ........................... <>
  [620] extcall 313 ............................. <list()>
  [623] setglobal 327 ........................... csTarot = list()
  [626] pusharglist 0 ........................... <>
  [628] extcall 313 ............................. <list()>
  [631] setglobal 204 ........................... csWagerTarot = list()
  [633] pusharglist 0 ........................... <>
  [635] extcall 313 ............................. <list()>
  [638] setglobal 448 ........................... csMansion = list()
  [641] pusharglist 0 ........................... <>
  [643] extcall 313 ............................. <list()>
  [646] setglobal 344 ........................... csDEL = list()
  [649] pusharglist 0 ........................... <>
  [651] extcall 313 ............................. <list()>
  [654] setglobal 345 ........................... csHEX = list()
  [657] pusharglist 0 ........................... <>
  [659] extcall 313 ............................. <list()>
  [662] setglobal 346 ........................... csREM = list()
  [665] pusharglist 0 ........................... <>
  [667] extcall 313 ............................. <list()>
  [670] setglobal 525 ........................... csCON = list()
  [673] pushzero ................................ <0>
  [674] setglobal 293 ........................... pTotalSwords = 0
  [677] pushzero ................................ <0>
  [678] setglobal 294 ........................... pTotalWands = 0
  [681] pushzero ................................ <0>
  [682] setglobal 295 ........................... pTotalCups = 0
  [685] pushzero ................................ <0>
  [686] setglobal 296 ........................... pTotalPentacles = 0
  [689] pushcons 0 .............................. <EMPTY>
  [691] setglobal 454 ........................... mouseChunk = EMPTY
  [694] pushzero ................................ <0>
  [695] setglobal 452 ........................... lastMouseX = 0
  [698] pushzero ................................ <0>
  [699] setglobal 453 ........................... lastMouseY = 0
  [702] pushcons 0 .............................. <EMPTY>
  [704] setglobal 457 ........................... keyChunk = EMPTY
  [707] pushzero ................................ <0>
  [708] setglobal 254 ........................... pClickToContinue = 0
  [710] pushzero ................................ <0>
  [711] setlocal 3 .............................. pTraceMenu = 0
  [713] pushzero ................................ <0>
  [714] setglobal 603 ........................... status_Quit_The_Game = 0
  [717] pushzero ................................ <0>
  [718] setglobal 648 ........................... pz_Total = 0
  [721] pushzero ................................ <0>
  [722] setglobal 649 ........................... pz_LastLaunch = 0
  [725] pusharglist 0 ........................... <>
  [727] extcall 313 ............................. <list()>
  [730] setglobal 650 ........................... pz_Available = list()
  [733] pusharglist 0 ........................... <>
  [735] extcall 313 ............................. <list()>
  [738] setglobal 390 ........................... menuName = list()
  [741] pusharglist 0 ........................... <>
  [743] extcall 313 ............................. <list()>
  [746] setglobal 92 ............................ menuStat = list()
  [748] pusharglist 0 ........................... <>
  [750] extcall 313 ............................. <list()>
  [753] setglobal 471 ........................... titleName = list()
  [756] pusharglist 0 ........................... <>
  [758] extcall 313 ............................. <list()>
  [761] setglobal 199 ........................... token1 = list()
  [763] pusharglist 0 ........................... <>
  [765] extcall 313 ............................. <list()>
  [768] setglobal 200 ........................... token2 = list()
  [770] pusharglist 0 ........................... <>
  [772] extcall 313 ............................. <list()>
  [775] setglobal 201 ........................... token3 = list()
  [777] pusharglist 0 ........................... <>
  [779] extcall 313 ............................. <list()>
  [782] setglobal 485 ........................... activity_Array = list()
  [785] pushzero ................................ <0>
  [786] setglobal 484 ........................... activity_Count = 0
  [789] pushzero ................................ <0>
  [790] setglobal 483 ........................... activity_Total = 0
  [793] pushzero ................................ <0>
  [794] setglobal 482 ........................... activity_Launch = 0
  [797] pusharglistnoret 0 ...................... <>
  [799] extcall 494 ............................. activity_Init()
  [802] pusharglist 0 ........................... <>
  [804] extcall 313 ............................. <list()>
  [807] setglobal 315 ........................... r1 = list()
  [810] pusharglist 0 ........................... <>
  [812] extcall 313 ............................. <list()>
  [815] setglobal 318 ........................... r2 = list()
  [818] pusharglist 0 ........................... <>
  [820] extcall 313 ............................. <list()>
  [823] setglobal 423 ........................... r3 = list()
  [826] pusharglist 0 ........................... <>
  [828] extcall 313 ............................. <list()>
  [831] setglobal 424 ........................... R4 = list()
  [834] pushzero ................................ <0>
  [835] setglobal 422 ........................... rectTotal = 0
  [838] pushint8 57 ............................. <57>
  [840] pushint16 571 ........................... <571>
  [843] pushint8 74 ............................. <74>
  [845] pushint8 28 ............................. <28>
  [847] pusharglistnoret 4 ...................... <57, 571, 74, 28>
  [849] extcall 395 ............................. misc_MakeRect(57, 571, 74, 28)
  [852] pushint16 163 ........................... <163>
  [855] pushint16 571 ........................... <571>
  [858] pushint8 65 ............................. <65>
  [860] pushint8 28 ............................. <28>
  [862] pusharglistnoret 4 ...................... <163, 571, 65, 28>
  [864] extcall 395 ............................. misc_MakeRect(163, 571, 65, 28)
  [867] pushint16 260 ........................... <260>
  [870] pushint16 571 ........................... <571>
  [873] pushint8 41 ............................. <41>
  [875] pushint8 28 ............................. <28>
  [877] pusharglistnoret 4 ...................... <260, 571, 41, 28>
  [879] extcall 395 ............................. misc_MakeRect(260, 571, 41, 28)
  [882] pushint16 338 ........................... <338>
  [885] pushint16 571 ........................... <571>
  [888] pushint8 49 ............................. <49>
  [890] pushint8 28 ............................. <28>
  [892] pusharglistnoret 4 ...................... <338, 571, 49, 28>
  [894] extcall 395 ............................. misc_MakeRect(338, 571, 49, 28)
  [897] pushint16 423 ........................... <423>
  [900] pushint16 571 ........................... <571>
  [903] pushint8 48 ............................. <48>
  [905] pushint8 28 ............................. <28>
  [907] pusharglistnoret 4 ...................... <423, 571, 48, 28>
  [909] extcall 395 ............................. misc_MakeRect(423, 571, 48, 28)
  [912] pushint16 508 ........................... <508>
  [915] pushint16 571 ........................... <571>
  [918] pushint8 72 ............................. <72>
  [920] pushint8 28 ............................. <28>
  [922] pusharglistnoret 4 ...................... <508, 571, 72, 28>
  [924] extcall 395 ............................. misc_MakeRect(508, 571, 72, 28)
  [927] pushint16 611 ........................... <611>
  [930] pushint16 571 ........................... <571>
  [933] pushint8 53 ............................. <53>
  [935] pushint8 28 ............................. <28>
  [937] pusharglistnoret 4 ...................... <611, 571, 53, 28>
  [939] extcall 395 ............................. misc_MakeRect(611, 571, 53, 28)
  [942] pushint16 696 ........................... <696>
  [945] pushint16 571 ........................... <571>
  [948] pushint8 43 ............................. <43>
  [950] pushint8 28 ............................. <28>
  [952] pusharglistnoret 4 ...................... <696, 571, 43, 28>
  [954] extcall 395 ............................. misc_MakeRect(696, 571, 43, 28)
  [957] pushcons 1 .............................. <"--------">
  [959] setglobal 449 ........................... menu_Key = "--------"
  [962] pushint8 1 .............................. <1>
  [964] pushint8 6 .............................. <6>
  [966] pushint8 2 .............................. <2>
  [968] pushint8 7 .............................. <7>
  [970] pushint8 3 .............................. <3>
  [972] pushint8 8 .............................. <8>
  [974] pushint8 4 .............................. <4>
  [976] pushint8 9 .............................. <9>
  [978] pushint8 5 .............................. <5>
  [980] pusharglist 9 ........................... <[1, 6, 2, 7, 3, 8, 4, 9, 5]>
  [982] pushlist ................................ <[1, 6, 2, 7, 3, 8, 4, 9, 5]>
  [983] setglobal 479 ........................... menuClick_Array = [1, 6, 2, 7, 3, 8, 4, 9, 5]
  [986] pushzero ................................ <0>
  [987] setglobal 478 ........................... menuClick_Count = 0
  [990] pusharglist 0 ........................... <>
  [992] extcall 313 ............................. <list()>
  [995] setglobal 489 ........................... snd_Channel_Array = list()
  [998] pushzero ................................ <0>
  [999] setglobal 477 ........................... snd_Channel_Count = 0
  [1002] pushint8 1 ............................. <1>
  [1004] setlocal 4
  [1006] getlocal 4
  [1008] pushint8 8 ............................. <8>
  [1010] lteq
  [1011] jmpifz [1042] .......................... repeat with x = 1 to 8
  [1014] getglobal 489 .......................... <snd_Channel_Array>
  [1017] getlocal 4 ............................. <x>
  [1019] gettoplevelprop 638 .................... <_sound>
  [1022] getlocal 4 ............................. <x>
  [1024] pusharglist 2 .......................... <_sound, x>
  [1026] objcall 651 ............................ <_sound.channel(x)>
  [1029] pusharglistnoret 3 ..................... <snd_Channel_Array, x, _sound.channel(x)>
  [1031] objcall 35 ............................. snd_Channel_Array[x] = _sound.channel(x)
  [1033] pushint8 1
  [1035] getlocal 4
  [1037] add
  [1038] setlocal 4
  [1040] endrepeat [1006]
  [1042] pushzero ............................... <0>
  [1043] setglobal 55 ........................... currRollOver = 0
  [1045] pushzero ............................... <0>
  [1046] setglobal 65 ........................... lastRollOver = 0
  [1048] pushzero ............................... <0>
  [1049] setglobal 96 ........................... currMenuDisplay = 0
  [1051] pushcons 0 ............................. <EMPTY>
  [1053] setglobal 506 .......................... chunkMenuName = EMPTY
  [1056] pushcons 0 ............................. <EMPTY>
  [1058] setglobal 333 .......................... chunkMenuStat = EMPTY
  [1061] pushzero ............................... <0>
  [1062] setglobal 514 .......................... directToScreenHelp = 0
  [1065] pushzero ............................... <0>
  [1066] setglobal 11 ........................... loadPuzzleCount = 0
  [1068] pushcons 0 ............................. <EMPTY>
  [1070] setglobal 205 .......................... pWindowCode = EMPTY
  [1072] pushzero ............................... <0>
  [1073] setglobal 168 .......................... currGame = 0
  [1075] getglobal 202 .......................... <cTokens>
  [1077] setglobal 328 .......................... lastPuzzle = cTokens
  [1080] getglobal 21 ........................... <cGameMenus>
  [1082] setglobal 24 ........................... currPuzzle = cGameMenus
  [1084] pushzero ............................... <0>
  [1085] setglobal 97 ........................... nextPuzzle = 0
  [1087] pushzero ............................... <0>
  [1088] setglobal 45 ........................... playMode = 0
  [1090] pushzero ............................... <0>
  [1091] setglobal 91 ........................... pmZero = 0
  [1093] pushint8 1 ............................. <1>
  [1095] setglobal 46 ........................... pmPlay = 1
  [1097] pushint8 2 ............................. <2>
  [1099] setglobal 102 .......................... pmHelp = 2
  [1101] pushint8 3 ............................. <3>
  [1103] setglobal 69 ........................... pmClick = 3
  [1105] pushint8 5 ............................. <5>
  [1107] setglobal 72 ........................... pmSave = 5
  [1109] pushint16 9999 ......................... <9999>
  [1112] setglobal 75 ........................... pmDeActivate = 9999
  [1114] pushint16 10000 ........................ <10000>
  [1117] setglobal 78 ........................... pmActivate = 10000
  [1119] pushzero ............................... <0>
  [1120] setlocal 5 ............................. _Pause_Play = 0
  [1122] pushzero ............................... <0>
  [1123] setlocal 6 ............................. _Pause_Goal = 0
  [1125] pushzero ............................... <0>
  [1126] setglobal 13 ........................... pFin_Count = 0
  [1128] pushzero ............................... <0>
  [1129] setglobal 95 ........................... pFin_Incre = 0
  [1131] pushzero ............................... <0>
  [1132] setglobal 12 ........................... pFin_Total = 0
  [1134] gettoplevelprop 14 ..................... <_movie>
  [1136] pusharglist 1 .......................... <_movie>
  [1138] objcall 469 ............................ <_movie.ticks()>
  [1141] setglobal 468 .......................... startTicks = _movie.ticks()
  [1144] gettoplevelprop 14 ..................... <_movie>
  [1146] pusharglist 1 .......................... <_movie>
  [1148] objcall 469 ............................ <_movie.ticks()>
  [1151] setmovieprop 652 ....................... the randomSeed = _movie.ticks()
  [1154] pushzero ............................... <0>
  [1155] setglobal 240 .......................... _Save_Stat = 0
  [1157] pushzero ............................... <0>
  [1158] setglobal 241 .......................... _Save_Type = 0
  [1160] pushint8 1 ............................. <1>
  [1162] setlocal 4
  [1164] getlocal 4
  [1166] getglobal 262 .......................... <cPuzzleTotal>
  [1169] lteq
  [1170] jmpifz [1307] .......................... repeat with x = 1 to cPuzzleTotal
  [1173] getglobal 365 .......................... <pNum>
  [1176] getlocal 4 ............................. <x>
  [1178] pushint8 1 ............................. <1>
  [1180] pusharglistnoret 3 ..................... <pNum, x, 1>
  [1182] objcall 35 ............................. pNum[x] = 1
  [1184] getglobal 93 ........................... <pStat>
  [1186] getlocal 4 ............................. <x>
  [1188] pushzero ............................... <0>
  [1189] pusharglistnoret 3 ..................... <pStat, x, 0>
  [1191] objcall 35 ............................. pStat[x] = 0
  [1193] getglobal 188 .......................... <pData>
  [1195] getlocal 4 ............................. <x>
  [1197] pushcons 2 ............................. <"empty">
  [1199] pusharglistnoret 3 ..................... <pData, x, "empty">
  [1201] objcall 35 ............................. pData[x] = "empty"
  [1203] getglobal 189 .......................... <pDone>
  [1205] getlocal 4 ............................. <x>
  [1207] pushcons 3 ............................. <"-">
  [1209] pusharglistnoret 3 ..................... <pDone, x, "-">
  [1211] objcall 35 ............................. pDone[x] = "-"
  [1213] getglobal 183 .......................... <pSwords>
  [1215] getlocal 4 ............................. <x>
  [1217] pushzero ............................... <0>
  [1218] pusharglistnoret 3 ..................... <pSwords, x, 0>
  [1220] objcall 35 ............................. pSwords[x] = 0
  [1222] getglobal 184 .......................... <pWands>
  [1224] getlocal 4 ............................. <x>
  [1226] pushzero ............................... <0>
  [1227] pusharglistnoret 3 ..................... <pWands, x, 0>
  [1229] objcall 35 ............................. pWands[x] = 0
  [1231] getglobal 185 .......................... <pCups>
  [1233] getlocal 4 ............................. <x>
  [1235] pushzero ............................... <0>
  [1236] pusharglistnoret 3 ..................... <pCups, x, 0>
  [1238] objcall 35 ............................. pCups[x] = 0
  [1240] getglobal 186 .......................... <pPentacles>
  [1242] getlocal 4 ............................. <x>
  [1244] pushzero ............................... <0>
  [1245] pusharglistnoret 3 ..................... <pPentacles, x, 0>
  [1247] objcall 35 ............................. pPentacles[x] = 0
  [1249] getglobal 100 .......................... <pPage>
  [1251] getlocal 4 ............................. <x>
  [1253] pushzero ............................... <0>
  [1254] pusharglistnoret 3 ..................... <pPage, x, 0>
  [1256] objcall 35 ............................. pPage[x] = 0
  [1258] getglobal 34 ........................... <pMenu>
  [1260] getlocal 4 ............................. <x>
  [1262] pushcons 4 ............................. <"12345--8">
  [1264] pusharglistnoret 3 ..................... <pMenu, x, "12345--8">
  [1266] objcall 35 ............................. pMenu[x] = "12345--8"
  [1268] getglobal 390 .......................... <menuName>
  [1271] getlocal 4 ............................. <x>
  [1273] pushcons 0 ............................. <EMPTY>
  [1275] pusharglistnoret 3 ..................... <menuName, x, EMPTY>
  [1277] objcall 35 ............................. menuName[x] = EMPTY
  [1279] getglobal 92 ........................... <menuStat>
  [1281] getlocal 4 ............................. <x>
  [1283] pushzero ............................... <0>
  [1284] pusharglistnoret 3 ..................... <menuStat, x, 0>
  [1286] objcall 35 ............................. menuStat[x] = 0
  [1288] getglobal 101 .......................... <pHelp>
  [1290] getlocal 4 ............................. <x>
  [1292] pushcons 0 ............................. <EMPTY>
  [1294] pusharglistnoret 3 ..................... <pHelp, x, EMPTY>
  [1296] objcall 35 ............................. pHelp[x] = EMPTY
  [1298] pushint8 1
  [1300] getlocal 4
  [1302] add
  [1303] setlocal 4
  [1305] endrepeat [1164]
  [1307] getglobal 34 ........................... <pMenu>
  [1309] getglobal 290 .......................... <cMoonsMap>
  [1312] pushcons 5 ............................. <"12-45--8">
  [1314] pusharglistnoret 3 ..................... <pMenu, cMoonsMap, "12-45--8">
  [1316] objcall 35 ............................. pMenu[cMoonsMap] = "12-45--8"
  [1318] getglobal 34 ........................... <pMenu>
  [1320] getglobal 291 .......................... <cMoonsPuzzles>
  [1323] pushcons 5 ............................. <"12-45--8">
  [1325] pusharglistnoret 3 ..................... <pMenu, cMoonsPuzzles, "12-45--8">
  [1327] objcall 35 ............................. pMenu[cMoonsPuzzles] = "12-45--8"
  [1329] getglobal 34 ........................... <pMenu>
  [1331] getglobal 21 ........................... <cGameMenus>
  [1333] pushcons 6 ............................. <"1-345--8">
  [1335] pusharglistnoret 3 ..................... <pMenu, cGameMenus, "1-345--8">
  [1337] objcall 35 ............................. pMenu[cGameMenus] = "1-345--8"
  [1339] getglobal 34 ........................... <pMenu>
  [1341] getglobal 247 .......................... <cHelpTokens>
  [1343] pushcons 7 ............................. <"1234---8">
  [1345] pusharglistnoret 3 ..................... <pMenu, cHelpTokens, "1234---8">
  [1347] objcall 35 ............................. pMenu[cHelpTokens] = "1234---8"
  [1349] pushzero ............................... <0>
  [1350] setglobal 293 .......................... pTotalSwords = 0
  [1353] pushzero ............................... <0>
  [1354] setglobal 294 .......................... pTotalWands = 0
  [1357] pushzero ............................... <0>
  [1358] setglobal 295 .......................... pTotalCups = 0
  [1361] pushzero ............................... <0>
  [1362] setglobal 296 .......................... pTotalPentacles = 0
  [1365] pushint8 1 ............................. <1>
  [1367] setlocal 4
  [1369] getlocal 4
  [1371] getglobal 195 .......................... <cFileTotal>
  [1373] lteq
  [1374] jmpifz [1415] .......................... repeat with x = 1 to cFileTotal
  [1377] getglobal 199 .......................... <token1>
  [1379] getlocal 4 ............................. <x>
  [1381] pushcons 0 ............................. <EMPTY>
  [1383] pusharglistnoret 3 ..................... <token1, x, EMPTY>
  [1385] objcall 35 ............................. token1[x] = EMPTY
  [1387] getglobal 200 .......................... <token2>
  [1389] getlocal 4 ............................. <x>
  [1391] pushcons 0 ............................. <EMPTY>
  [1393] pusharglistnoret 3 ..................... <token2, x, EMPTY>
  [1395] objcall 35 ............................. token2[x] = EMPTY
  [1397] getglobal 201 .......................... <token3>
  [1399] getlocal 4 ............................. <x>
  [1401] pushzero ............................... <0>
  [1402] pusharglistnoret 3 ..................... <token3, x, 0>
  [1404] objcall 35 ............................. token3[x] = 0
  [1406] pushint8 1
  [1408] getlocal 4
  [1410] add
  [1411] setlocal 4
  [1413] endrepeat [1369]
  [1415] pusharglistnoret 0 ..................... <>
  [1417] extcall 542 ............................ token_ClearSaved()
  [1420] pusharglistnoret 0 ..................... <>
  [1422] extcall 516 ............................ gatherAllData()
  [1425] pushcons 8 ............................. <"The Tower">
  [1427] pushcons 9 ............................. <"The Magician">
  [1429] pushcons 10 ............................ <"The Star">
  [1431] pushcons 11 ............................ <"The Hermit">
  [1433] pushcons 12 ............................ <"Strength">
  [1435] pushcons 13 ............................ <"The Devil">
  [1437] pushcons 14 ............................ <"The Hierophant">
  [1439] pushcons 15 ............................ <"The Empress">
  [1441] pushcons 16 ............................ <"The Chariot">
  [1443] pushcons 17 ............................ <"Justice">
  [1445] pushcons 18 ............................ <"Death">
  [1447] pushcons 19 ............................ <"The Lovers">
  [1449] pusharglist 12 ......................... <["The Tower", "The Magician", "The Star", "The Hermit", "Strength", "The Devil", "The Hierophant", "The Empress", "The Chariot", "Justice", "Death", "The Lovers"]>
  [1451] pushlist ............................... <["The Tower", "The Magician", "The Star", "The Hermit", "Strength", "The Devil", "The Hierophant", "The Empress", "The Chariot", "Justice", "Death", "The Lovers"]>
  [1452] setglobal 258 .......................... cTarotCards = ["The Tower", "The Magician", "The Star", "The Hermit", "Strength", "The Devil", "The Hierophant", "The Empress", "The Chariot", "Justice", "Death", "The Lovers"]
  [1455] pushcons 20 ............................ <"Tower">
  [1457] pushcons 21 ............................ <"Magician">
  [1459] pushcons 22 ............................ <"Star">
  [1461] pushcons 23 ............................ <"Hermit">
  [1463] pushcons 12 ............................ <"Strength">
  [1465] pushcons 24 ............................ <"Devil">
  [1467] pushcons 25 ............................ <"Hierophant">
  [1469] pushcons 26 ............................ <"Empress">
  [1471] pushcons 27 ............................ <"Chariot">
  [1473] pushcons 17 ............................ <"Justice">
  [1475] pushcons 18 ............................ <"Death">
  [1477] pushcons 28 ............................ <"Lovers">
  [1479] pusharglist 12 ......................... <["Tower", "Magician", "Star", "Hermit", "Strength", "Devil", "Hierophant", "Empress", "Chariot", "Justice", "Death", "Lovers"]>
  [1481] pushlist ............................... <["Tower", "Magician", "Star", "Hermit", "Strength", "Devil", "Hierophant", "Empress", "Chariot", "Justice", "Death", "Lovers"]>
  [1482] setlocal 7 ............................. shortened = ["Tower", "Magician", "Star", "Hermit", "Strength", "Devil", "Hierophant", "Empress", "Chariot", "Justice", "Death", "Lovers"]
  [1484] pushint8 1 ............................. <1>
  [1486] setlocal 4
  [1488] getlocal 4
  [1490] pushint8 12 ............................ <12>
  [1492] lteq
  [1493] jmpifz [1576] .......................... repeat with x = 1 to 12
  [1496] getglobal 178 .......................... <tName>
  [1498] getlocal 4 ............................. <x>
  [1500] getglobal 509 .......................... <cSavedGamesDirectory>
  [1503] getglobal 158 .......................... <prefNumber>
  [1505] getlocal 4 ............................. <x>
  [1507] pusharglist 2 .......................... <prefNumber, x>
  [1509] objcall 17 ............................. <prefNumber[x]>
  [1511] pushsymb 135 ........................... <#char>
  [1513] pushint8 1 ............................. <1>
  [1515] pushint8 2 ............................. <2>
  [1517] pusharglist 4 .......................... <prefNumber[x], #char, 1, 2>
  [1519] objcall 136 ............................ <prefNumber[x].char[1..2]>
  [1521] joinstr ................................ <cSavedGamesDirectory & prefNumber[x].char[1..2]>
  [1522] pushcons 3 ............................. <"-">
  [1524] joinstr ................................ <cSavedGamesDirectory & prefNumber[x].char[1..2] & "-">
  [1525] getlocal 7 ............................. <shortened>
  [1527] getlocal 4 ............................. <x>
  [1529] pusharglist 2 .......................... <shortened, x>
  [1531] objcall 17 ............................. <shortened[x]>
  [1533] joinstr ................................ <cSavedGamesDirectory & prefNumber[x].char[1..2] & "-" & shortened[x]>
  [1534] pushcons 29 ............................ <".txt">
  [1536] joinstr ................................ <cSavedGamesDirectory & prefNumber[x].char[1..2] & "-" & shortened[x] & ".txt">
  [1537] pusharglistnoret 3 ..................... <tName, x, cSavedGamesDirectory & prefNumber[x].char[1..2] & "-" & shortened[x] & ".txt">
  [1539] objcall 35 ............................. tName[x] = cSavedGamesDirectory & prefNumber[x].char[1..2] & "-" & shortened[x] & ".txt"
  [1541] getglobal 143 .......................... <fName>
  [1543] getlocal 4 ............................. <x>
  [1545] getglobal 178 .......................... <tName>
  [1547] getlocal 4 ............................. <x>
  [1549] pusharglist 2 .......................... <tName, x>
  [1551] objcall 17 ............................. <tName[x]>
  [1553] pusharglistnoret 3 ..................... <fName, x, tName[x]>
  [1555] objcall 35 ............................. fName[x] = tName[x]
  [1557] getglobal 155 .......................... <fData>
  [1559] getlocal 4 ............................. <x>
  [1561] pushcons 0 ............................. <EMPTY>
  [1563] pusharglistnoret 3 ..................... <fData, x, EMPTY>
  [1565] objcall 35 ............................. fData[x] = EMPTY
  [1567] pushint8 1
  [1569] getlocal 4
  [1571] add
  [1572] setlocal 4
  [1574] endrepeat [1488]
  [1576] getglobal 155 .......................... <fData>
  [1578] getglobal 179 .......................... <cNewGameNum>
  [1580] pushcons 30 ............................ <"new-game">
  [1582] pushzero ............................... <0>
  [1583] getfield ............................... <field("new-game")>
  [1584] pusharglistnoret 3 ..................... <fData, cNewGameNum, field("new-game")>
  [1586] objcall 35 ............................. fData[cNewGameNum] = field("new-game")
  [1588] getglobal 179 .......................... <cNewGameNum>
  [1590] pusharglistnoret 1 ..................... <cNewGameNum>
  [1592] extcall 125 ............................ parseTokenDescriptions(cNewGameNum)
  [1594] getglobal 143 .......................... <fName>
  [1596] getglobal 161 .......................... <cOpenGameNum>
  [1598] pushcons 0 ............................. <EMPTY>
  [1600] pusharglistnoret 3 ..................... <fName, cOpenGameNum, EMPTY>
  [1602] objcall 35 ............................. fName[cOpenGameNum] = EMPTY
  [1604] getglobal 155 .......................... <fData>
  [1606] getglobal 161 .......................... <cOpenGameNum>
  [1608] pushcons 0 ............................. <EMPTY>
  [1610] pusharglistnoret 3 ..................... <fData, cOpenGameNum, EMPTY>
  [1612] objcall 35 ............................. fData[cOpenGameNum] = EMPTY
  [1614] pusharglist 0 .......................... <>
  [1616] extcall 501 ............................ <getLastGamePref()>
  [1619] setglobal 168 .......................... currGame = getLastGamePref()
  [1621] pushint8 1 ............................. <1>
  [1623] setlocal 4
  [1625] getlocal 4
  [1627] getglobal 181 .......................... <cTarotTotal>
  [1629] lteq
  [1630] jmpifz [1745] .......................... repeat with x = 1 to cTarotTotal
  [1633] pushzero ............................... <0>
  [1634] setlocal 8 ............................. savedGamesFolder = 0
  [1636] getglobal 155 .......................... <fData>
  [1638] getlocal 4 ............................. <x>
  [1640] getlocal 4 ............................. <x>
  [1642] pusharglist 1 .......................... <x>
  [1644] extcall 104 ............................ <getFoolFile(x)>
  [1646] pusharglistnoret 3 ..................... <fData, x, getFoolFile(x)>
  [1648] objcall 35 ............................. fData[x] = getFoolFile(x)
  [1650] getglobal 155 .......................... <fData>
  [1652] getlocal 4 ............................. <x>
  [1654] pusharglist 2 .......................... <fData, x>
  [1656] objcall 17 ............................. <fData[x]>
  [1658] pushcons 0 ............................. <EMPTY>
  [1660] nteq ................................... <fData[x] <> EMPTY>
  [1661] jmpifz [1686] .......................... if fData[x] <> EMPTY then
  [1664] getglobal 155 .......................... <fData>
  [1666] getlocal 4 ............................. <x>
  [1668] pusharglist 2 .......................... <fData, x>
  [1670] objcall 17 ............................. <fData[x]>
  [1672] pusharglist 1 .......................... <fData[x]>
  [1674] extcall 147 ............................ <zipTest(fData[x])>
  [1676] pushint8 1 ............................. <1>
  [1678] eq ..................................... <zipTest(fData[x]) = 1>
  [1679] jmpifz [1686] .......................... if zipTest(fData[x]) = 1 then
  [1682] pushint8 1 ............................. <1>
  [1684] setlocal 8 ............................. savedGamesFolder = 1
  [1686] getlocal 8 ............................. <savedGamesFolder>
  [1688] pushzero ............................... <0>
  [1689] eq ..................................... <savedGamesFolder = 0>
  [1690] jmpifz [1730] .......................... if savedGamesFolder = 0 then
  [1693] pushcons 31 ............................ <"NO save">
  [1695] getglobal 158 .......................... <prefNumber>
  [1697] getlocal 4 ............................. <x>
  [1699] pusharglist 2 .......................... <prefNumber, x>
  [1701] objcall 17 ............................. <prefNumber[x]>
  [1703] joinpadstr ............................. <"NO save" && prefNumber[x]>
  [1704] pusharglistnoret 1 ..................... <"NO save" && prefNumber[x]>
  [1706] extcall 174 ............................ _PUT("NO save" && prefNumber[x])
  [1708] getglobal 155 .......................... <fData>
  [1710] getlocal 4 ............................. <x>
  [1712] getglobal 155 .......................... <fData>
  [1714] getglobal 179 .......................... <cNewGameNum>
  [1716] pusharglist 2 .......................... <fData, cNewGameNum>
  [1718] objcall 17 ............................. <fData[cNewGameNum]>
  [1720] pusharglistnoret 3 ..................... <fData, x, fData[cNewGameNum]>
  [1722] objcall 35 ............................. fData[x] = fData[cNewGameNum]
  [1724] getlocal 4 ............................. <x>
  [1726] pusharglistnoret 1 ..................... <x>
  [1728] extcall 107 ............................ putFoolFileSavedGamesFolder(x)
  [1730] getlocal 4 ............................. <x>
  [1732] pusharglistnoret 1 ..................... <x>
  [1734] extcall 125 ............................ parseTokenDescriptions(x)
  [1736] pushint8 1
  [1738] getlocal 4
  [1740] add
  [1741] setlocal 4
  [1743] endrepeat [1625]
  [1745] getglobal 168 .......................... <currGame>
  [1747] pusharglistnoret 1 ..................... <currGame>
  [1749] extcall 173 ............................ readGameFile(currGame)
  [1751] gettoplevelprop 14 ..................... <_movie>
  [1753] pushint8 3 ............................. <3>
  [1755] pusharglistnoret 2 ..................... <_movie, 3>
  [1757] objcall 18 ............................. _movie.go(3)
  [1759] ret
end

on init_NewGameData chunk
  [  0] getglobal 155 ........................... <fData>
  [  2] getglobal 179 ........................... <cNewGameNum>
  [  4] getparam 0 .............................. <chunk>
  [  6] pusharglistnoret 3 ...................... <fData, cNewGameNum, chunk>
  [  8] objcall 35 .............................. fData[cNewGameNum] = chunk
  [ 10] pushcons 30 ............................. <"new-game">
  [ 12] pusharglist 1 ........................... <"new-game">
  [ 14] extcall 612 ............................. <member("new-game")>
  [ 17] getparam 0 .............................. <chunk>
  [ 19] setobjprop 657 .......................... member("new-game").text = chunk
  [ 22] pushcons 32 ............................. <"New Game Data created">
  [ 24] pusharglistnoret 1 ...................... <"New Game Data created">
  [ 26] extcall 174 ............................. _PUT("New Game Data created")
  [ 28] pusharglistnoret 0 ...................... <>
  [ 30] extcall 609 ............................. halt()
  [ 33] ret
end

on init_LaunchGame
  [  0] pushzero ................................ <0>
  [  1] setlocal 0 .............................. b1 = 0
  [  3] pushzero ................................ <0>
  [  4] setlocal 1 .............................. b2 = 0
  [  6] getglobal 57 ............................ <cScrollSN>
  [  8] pusharglist 1 ........................... <cScrollSN>
  [ 10] extcall 429 ............................. <sprite(cScrollSN)>
  [ 13] pushcons 33 ............................. <"initPage">
  [ 15] pushint8 1 .............................. <1>
  [ 17] pusharglist 3 ........................... <sprite(cScrollSN), "initPage", 1>
  [ 19] objcall 440 ............................. <sprite(cScrollSN).getVariable("initPage", 1)>
  [ 22] pushcons 34 ............................. <"666">
  [ 24] nteq .................................... <sprite(cScrollSN).getVariable("initPage", 1) <> "666">
  [ 25] jmpifz [ 38] ............................ if sprite(cScrollSN).getVariable("initPage", 1) <> "666" then / else
  [ 28] getglobal 57 ............................ <cScrollSN>
  [ 30] pusharglistnoret 1 ...................... <cScrollSN>
  [ 32] extcall 399 ............................. misc_CallSprite(cScrollSN)
  [ 35] jmp [ 42]
  [ 38] pushint8 1 .............................. <1>
  [ 40] setlocal 0 .............................. b1 = 1
  [ 42] getglobal 265 ........................... <cHelpSN>
  [ 45] pusharglist 1 ........................... <cHelpSN>
  [ 47] extcall 429 ............................. <sprite(cHelpSN)>
  [ 50] pushcons 35 ............................. <"initHelp">
  [ 52] pushint8 1 .............................. <1>
  [ 54] pusharglist 3 ........................... <sprite(cHelpSN), "initHelp", 1>
  [ 56] objcall 440 ............................. <sprite(cHelpSN).getVariable("initHelp", 1)>
  [ 59] pushcons 34 ............................. <"666">
  [ 61] nteq .................................... <sprite(cHelpSN).getVariable("initHelp", 1) <> "666">
  [ 62] jmpifz [ 76] ............................ if sprite(cHelpSN).getVariable("initHelp", 1) <> "666" then / else
  [ 65] getglobal 265 ........................... <cHelpSN>
  [ 68] pusharglistnoret 1 ...................... <cHelpSN>
  [ 70] extcall 399 ............................. misc_CallSprite(cHelpSN)
  [ 73] jmp [ 80]
  [ 76] pushint8 1 .............................. <1>
  [ 78] setlocal 1 .............................. b2 = 1
  [ 80] getglobal 24 ............................ <currPuzzle>
  [ 82] pusharglist 1 ........................... <currPuzzle>
  [ 84] extcall 279 ............................. <_Help_Tokens_Exception(currPuzzle)>
  [ 87] setglobal 24 ............................ currPuzzle = _Help_Tokens_Exception(currPuzzle)
  [ 89] getlocal 0 .............................. <b1>
  [ 91] pushint8 1 .............................. <1>
  [ 93] eq ...................................... <b1 = 1>
  [ 94] getlocal 1 .............................. <b2>
  [ 96] pushint8 1 .............................. <1>
  [ 98] eq ...................................... <b2 = 1>
  [ 99] and ..................................... <(b1 = 1) and (b2 = 1)>
  [100] jmpifz [154] ............................ if (b1 = 1) and (b2 = 1) then
  [103] getglobal 745 ........................... <theDataStatus>
  [106] pushzero ................................ <0>
  [107] eq ...................................... <theDataStatus = 0>
  [108] jmpifz [121] ............................ if theDataStatus = 0 then / else
  [111] pushzero ................................ <0>
  [112] pushzero ................................ <0>
  [113] pusharglistnoret 2 ...................... <0, 0>
  [115] extcall 490 ............................. _Launch_Tokens(0, 0)
  [118] jmp [154]
  [121] getglobal 24 ............................ <currPuzzle>
  [123] pushzero ................................ <0>
  [124] eq ...................................... <currPuzzle = 0>
  [125] getglobal 168 ........................... <currGame>
  [127] pushzero ................................ <0>
  [128] eq ...................................... <currGame = 0>
  [129] or ...................................... <(currPuzzle = 0) or (currGame = 0)>
  [130] jmpifz [143] ............................ if (currPuzzle = 0) or (currGame = 0) then / else
  [133] pushzero ................................ <0>
  [134] pushzero ................................ <0>
  [135] pusharglistnoret 2 ...................... <0, 0>
  [137] extcall 490 ............................. _Launch_Tokens(0, 0)
  [140] jmp [154]
  [143] pushzero ................................ <0>
  [144] setglobal 382 ........................... status_First_Launch = 0
  [147] getglobal 24 ............................ <currPuzzle>
  [149] pushzero ................................ <0>
  [150] pusharglistnoret 2 ...................... <currPuzzle, 0>
  [152] extcall 20 .............................. initLaunch(currPuzzle, 0)
  [154] ret
end
