global cMenuSN, cRevGameNum, cNewGameNum, cPreFinale, cTokens, cPreHP, cEndHP, cHighPriestess, cSevenCups, cGameMenus, cFinale, cHelpTokens, cMoonsMap, cMoonsPuzzles, pStat, pHelp, pMenu, pMiscellaneous, pInfo, pFrame, pTransition, pPage, fName, fData, currGame, currPuzzle, lastPuzzle, theRequest, requestBlock, menuName, menuStat, token1, token2, token3, csWager, csTarot, csWagerTarot, tokens_LastPuzzle, tokens_CurrentGame, tokens_NeedToSave, status_First_Launch

on initRequest S
  [  0] getglobal 99 ............................ <requestBlock>
  [  2] getparam 0 .............................. <S>
  [  4] joinstr ................................. <requestBlock & S>
  [  5] setglobal 99 ............................ requestBlock = requestBlock & S
  [  7] ret
end

on extractRequest b
  [  0] getglobal 99 ............................ <requestBlock>
  [  2] pushcons 0 .............................. <EMPTY>
  [  4] nteq .................................... <requestBlock <> EMPTY>
  [  5] jmpifz [105] ............................ if requestBlock <> EMPTY then
  [  8] pushint8 1 .............................. <1>
  [ 10] setlocal 0 .............................. n1 = 1
  [ 12] pushint8 1 .............................. <1>
  [ 14] setlocal 1 .............................. n2 = 1
  [ 16] getglobal 99 ............................ <requestBlock>
  [ 18] pushsymb 135 ............................ <#char>
  [ 20] getlocal 1 .............................. <n2>
  [ 22] getlocal 1 .............................. <n2>
  [ 24] pusharglist 4 ........................... <requestBlock, #char, n2, n2>
  [ 26] objcall 136 ............................. <requestBlock.char[n2..n2]>
  [ 28] pushcons 1 .............................. <"|">
  [ 30] nteq .................................... <requestBlock.char[n2..n2] <> "|">
  [ 31] jmpifz [ 43] ............................ repeat while requestBlock.char[n2..n2] <> "|"
  [ 34] getlocal 1 .............................. <n2>
  [ 36] pushint8 1 .............................. <1>
  [ 38] add ..................................... <n2 + 1>
  [ 39] setlocal 1 .............................. n2 = n2 + 1
  [ 41] endrepeat [ 16]
  [ 43] getglobal 99 ............................ <requestBlock>
  [ 45] pushsymb 135 ............................ <#char>
  [ 47] getlocal 0 .............................. <n1>
  [ 49] getlocal 1 .............................. <n2>
  [ 51] pushint8 1 .............................. <1>
  [ 53] sub ..................................... <n2 - 1>
  [ 54] pusharglist 4 ........................... <requestBlock, #char, n1, n2 - 1>
  [ 56] objcall 136 ............................. <requestBlock.char[n1..n2 - 1]>
  [ 58] setlocal 2 .............................. S = requestBlock.char[n1..n2 - 1]
  [ 60] getglobal 99 ............................ <requestBlock>
  [ 62] pushsymb 135 ............................ <#char>
  [ 64] getlocal 1 .............................. <n2>
  [ 66] pushint8 1 .............................. <1>
  [ 68] add ..................................... <n2 + 1>
  [ 69] getglobal 99 ............................ <requestBlock>
  [ 71] getobjprop 134 .......................... <requestBlock.length>
  [ 73] pusharglist 4 ........................... <requestBlock, #char, n2 + 1, requestBlock.length>
  [ 75] objcall 136 ............................. <requestBlock.char[n2 + 1..requestBlock.length]>
  [ 77] setglobal 99 ............................ requestBlock = requestBlock.char[n2 + 1..requestBlock.length]
  [ 79] getparam 0 .............................. <b>
  [ 81] pushzero ................................ <0>
  [ 82] eq ...................................... <b = 0>
  [ 83] jmpifz [ 95] ............................ if b = 0 then / else
  [ 86] getlocal 2 .............................. <S>
  [ 88] pusharglistnoret 1 ...................... <S>
  [ 90] extcall 137 ............................. return S
  [ 92] jmp [105]
  [ 95] getlocal 2 .............................. <S>
  [ 97] pusharglist 1 ........................... <S>
  [ 99] extcall 42 .............................. <integer(S)>
  [101] pusharglistnoret 1 ...................... <integer(S)>
  [103] extcall 137 ............................. return integer(S)
  [105] ret
end

on _Launch_From_Map b
  [  0] pusharglistnoret 0 ...................... <>
  [  2] extcall 373 ............................. menu_Click_Snd()
  [  5] pushint8 1 .............................. <1>
  [  7] pusharglist 1 ........................... <1>
  [  9] localcall 1 ............................. <extractRequest(1)>
  [ 11] setlocal 0 .............................. N = extractRequest(1)
  [ 13] pushint8 1 .............................. <1>
  [ 15] setlocal 1
  [ 17] getlocal 1
  [ 19] pushint8 5 .............................. <5>
  [ 21] lteq
  [ 22] jmpifz [ 64] ............................ repeat with x = 1 to 5
  [ 25] getlocal 0 .............................. <N>
  [ 27] getglobal 217 ........................... <csWager>
  [ 29] getlocal 1 .............................. <x>
  [ 31] pusharglist 2 ........................... <csWager, x>
  [ 33] objcall 17 .............................. <csWager[x]>
  [ 35] eq ...................................... <N = csWager[x]>
  [ 36] jmpifz [ 55] ............................ if N = csWager[x] then
  [ 39] getglobal 204 ........................... <csWagerTarot>
  [ 41] getlocal 1 .............................. <x>
  [ 43] getglobal 217 ........................... <csWager>
  [ 45] getlocal 1 .............................. <x>
  [ 47] pusharglist 2 ........................... <csWager, x>
  [ 49] objcall 17 .............................. <csWager[x]>
  [ 51] pusharglistnoret 3 ...................... <csWagerTarot, x, csWager[x]>
  [ 53] objcall 35 .............................. csWagerTarot[x] = csWager[x]
  [ 55] pushint8 1
  [ 57] getlocal 1
  [ 59] add
  [ 60] setlocal 1
  [ 62] endrepeat [ 17]
  [ 64] getlocal 0 .............................. <N>
  [ 66] pushint8 1 .............................. <1>
  [ 68] pusharglistnoret 2 ...................... <N, 1>
  [ 70] extcall 20 .............................. initLaunch(N, 1)
  [ 72] getparam 0 .............................. <b>
  [ 74] pushint8 1 .............................. <1>
  [ 76] eq ...................................... <b = 1>
  [ 77] jmpifz [ 84] ............................ if b = 1 then
  [ 80] pushint8 9 .............................. <9>
  [ 82] setglobal 19 ............................ pTransition = 9
  [ 84] ret
end

on doSpecialRequests
  [  0] pushint8 1 .............................. <1>
  [  2] pusharglist 1 ........................... <1>
  [  4] localcall 1 ............................. <extractRequest(1)>
  [  6] setglobal 374 ........................... theRequest = extractRequest(1)
  [  9] getglobal 374 ........................... <theRequest>
  [ 12] peek 0 .................................. case theRequest of
  [ 14] pushzero ................................ <0>
  [ 15] eq
  [ 16] jmpifz [ 29] ............................ (case) 0:
  [ 19] pushcons 2 .............................. <"gFlashCommand">
  [ 21] pushzero ................................ <0>
  [ 22] pusharglistnoret 2 ...................... <"gFlashCommand", 0>
  [ 24] extcall 51 .............................. misc_SetFlash("gFlashCommand", 0)
  [ 26] jmp [1447]
  [ 29] peek 0
  [ 31] pushint8 1 .............................. <1>
  [ 33] eq
  [ 34] jmpifz [ 46] ............................ (case) 1:
  [ 37] pushint8 1 .............................. <1>
  [ 39] pusharglistnoret 1 ...................... <1>
  [ 41] localcall 2 ............................. _Launch_From_Map(1)
  [ 43] jmp [1447]
  [ 46] peek 0
  [ 48] pushint8 2 .............................. <2>
  [ 50] eq
  [ 51] jmpifz [ 62] ............................ (case) 2:
  [ 54] pushzero ................................ <0>
  [ 55] pusharglistnoret 1 ...................... <0>
  [ 57] localcall 2 ............................. _Launch_From_Map(0)
  [ 59] jmp [1447]
  [ 62] peek 0
  [ 64] pushint8 3 .............................. <3>
  [ 66] eq
  [ 67] jmpifz [ 87] ............................ (case) 3:
  [ 70] pushint8 1 .............................. <1>
  [ 72] pusharglist 1 ........................... <1>
  [ 74] localcall 1 ............................. <extractRequest(1)>
  [ 76] setlocal 0 .............................. Q = extractRequest(1)
  [ 78] getglobal 168 ........................... <currGame>
  [ 80] pusharglistnoret 1 ...................... <currGame>
  [ 82] extcall 196 ............................. updateGameStats(currGame)
  [ 84] jmp [1447]
  [ 87] peek 0
  [ 89] pushint8 4 .............................. <4>
  [ 91] eq
  [ 92] jmpifz [111] ............................ (case) 4:
  [ 95] getglobal 290 ........................... <cMoonsMap>
  [ 98] pushint8 1 .............................. <1>
  [100] pusharglistnoret 2 ...................... <cMoonsMap, 1>
  [102] extcall 20 .............................. initLaunch(cMoonsMap, 1)
  [104] pushint8 9 .............................. <9>
  [106] setglobal 19 ............................ pTransition = 9
  [108] jmp [1447]
  [111] peek 0
  [113] pushint8 5 .............................. <5>
  [115] eq
  [116] jmpifz [135] ............................ (case) 5:
  [119] getglobal 291 ........................... <cMoonsPuzzles>
  [122] pushint8 1 .............................. <1>
  [124] pusharglistnoret 2 ...................... <cMoonsPuzzles, 1>
  [126] extcall 20 .............................. initLaunch(cMoonsPuzzles, 1)
  [128] pushint8 9 .............................. <9>
  [130] setglobal 19 ............................ pTransition = 9
  [132] jmp [1447]
  [135] peek 0
  [137] pushint8 6 .............................. <6>
  [139] eq
  [140] jmpifz [159] ............................ (case) 6:
  [143] getglobal 285 ........................... <cSevenCups>
  [146] pushint8 1 .............................. <1>
  [148] pusharglistnoret 2 ...................... <cSevenCups, 1>
  [150] extcall 20 .............................. initLaunch(cSevenCups, 1)
  [152] pushint8 9 .............................. <9>
  [154] setglobal 19 ............................ pTransition = 9
  [156] jmp [1447]
  [159] peek 0
  [161] pushint8 7 .............................. <7>
  [163] eq
  [164] jmpifz [192] ............................ (case) 7:
  [167] getglobal 100 ........................... <pPage>
  [169] getglobal 98 ............................ <cPreFinale>
  [171] pushint8 2 .............................. <2>
  [173] pusharglistnoret 3 ...................... <pPage, cPreFinale, 2>
  [175] objcall 35 .............................. pPage[cPreFinale] = 2
  [177] getglobal 98 ............................ <cPreFinale>
  [179] pushint8 1 .............................. <1>
  [181] pusharglistnoret 2 ...................... <cPreFinale, 1>
  [183] extcall 20 .............................. initLaunch(cPreFinale, 1)
  [185] pushint8 9 .............................. <9>
  [187] setglobal 19 ............................ pTransition = 9
  [189] jmp [1447]
  [192] peek 0
  [194] pushint8 8 .............................. <8>
  [196] eq
  [197] jmpifz [224] ............................ (case) 8:
  [200] pusharglistnoret 0 ...................... <>
  [202] extcall 373 ............................. menu_Click_Snd()
  [205] pushint8 1 .............................. <1>
  [207] pusharglist 1 ........................... <1>
  [209] localcall 1 ............................. <extractRequest(1)>
  [211] pushint8 1 .............................. <1>
  [213] pusharglistnoret 2 ...................... <extractRequest(1), 1>
  [215] extcall 20 .............................. initLaunch(extractRequest(1), 1)
  [217] pushint8 9 .............................. <9>
  [219] setglobal 19 ............................ pTransition = 9
  [221] jmp [1447]
  [224] peek 0
  [226] pushint8 9 .............................. <9>
  [228] eq
  [229] jmpifz [252] ............................ (case) 9:
  [232] pusharglistnoret 0 ...................... <>
  [234] extcall 373 ............................. menu_Click_Snd()
  [237] pushint8 1 .............................. <1>
  [239] pusharglist 1 ........................... <1>
  [241] localcall 1 ............................. <extractRequest(1)>
  [243] pushint8 1 .............................. <1>
  [245] pusharglistnoret 2 ...................... <extractRequest(1), 1>
  [247] extcall 20 .............................. initLaunch(extractRequest(1), 1)
  [249] jmp [1447]
  [252] peek 0
  [254] pushint8 10 ............................. <10>
  [256] eq
  [257] jmpifz [275] ............................ (case) 10:
  [260] pushint8 1 .............................. <1>
  [262] pusharglist 1 ........................... <1>
  [264] localcall 1 ............................. <extractRequest(1)>
  [266] pushint8 1 .............................. <1>
  [268] pusharglistnoret 2 ...................... <extractRequest(1), 1>
  [270] extcall 20 .............................. initLaunch(extractRequest(1), 1)
  [272] jmp [1447]
  [275] peek 0
  [277] pushint8 13 ............................. <13>
  [279] eq
  [280] jmpifz [296] ............................ (case) 13:
  [283] pushint8 1 .............................. <1>
  [285] pusharglist 1 ........................... <1>
  [287] localcall 1 ............................. <extractRequest(1)>
  [289] pusharglistnoret 1 ...................... <extractRequest(1)>
  [291] extcall 28 .............................. misc_CalcPage(extractRequest(1))
  [293] jmp [1447]
  [296] peek 0
  [298] pushint8 14 ............................. <14>
  [300] eq
  [301] jmpifz [320] ............................ (case) 14:
  [304] getglobal 101 ........................... <pHelp>
  [306] getglobal 24 ............................ <currPuzzle>
  [308] pushzero ................................ <0>
  [309] pusharglist 1 ........................... <0>
  [311] localcall 1 ............................. <extractRequest(0)>
  [313] pusharglistnoret 3 ...................... <pHelp, currPuzzle, extractRequest(0)>
  [315] objcall 35 .............................. pHelp[currPuzzle] = extractRequest(0)
  [317] jmp [1447]
  [320] peek 0
  [322] pushint8 17 ............................. <17>
  [324] eq
  [325] jmpifz [350] ............................ (case) 17:
  [328] pusharglistnoret 0 ...................... <>
  [330] extcall 121 ............................. saveCurrentPuzzle()
  [332] getglobal 168 ........................... <currGame>
  [334] pusharglistnoret 1 ...................... <currGame>
  [336] extcall 196 ............................. updateGameStats(currGame)
  [338] pushcons 3 .............................. <"pInfo">
  [340] getglobal 301 ........................... <pInfo>
  [343] pusharglistnoret 2 ...................... <"pInfo", pInfo>
  [345] extcall 51 .............................. misc_SetFlash("pInfo", pInfo)
  [347] jmp [1447]
  [350] peek 0
  [352] pushint8 18 ............................. <18>
  [354] eq
  [355] jmpifz [382] ............................ (case) 18:
  [358] pusharglistnoret 0 ...................... <>
  [360] extcall 373 ............................. menu_Click_Snd()
  [363] pushint8 2 .............................. <2>
  [365] pusharglistnoret 1 ...................... <2>
  [367] extcall 375 ............................. menu_Frame(2)
  [370] getglobal 264 ........................... <cPreHP>
  [373] pushint8 1 .............................. <1>
  [375] pusharglistnoret 2 ...................... <cPreHP, 1>
  [377] extcall 20 .............................. initLaunch(cPreHP, 1)
  [379] jmp [1447]
  [382] peek 0
  [384] pushint8 19 ............................. <19>
  [386] eq
  [387] jmpifz [439] ............................ (case) 19:
  [390] pushzero ................................ <0>
  [391] pusharglist 1 ........................... <0>
  [393] localcall 1 ............................. <extractRequest(0)>
  [395] setlocal 1 .............................. S = extractRequest(0)
  [397] getlocal 1 .............................. <S>
  [399] getobjprop 134 .......................... <S.length>
  [401] pushint8 8 .............................. <8>
  [403] eq ...................................... <S.length = 8>
  [404] jmpifz [436] ............................ if S.length = 8 then
  [407] getlocal 1 .............................. <S>
  [409] getglobal 34 ............................ <pMenu>
  [411] getglobal 24 ............................ <currPuzzle>
  [413] pusharglist 2 ........................... <pMenu, currPuzzle>
  [415] objcall 17 .............................. <pMenu[currPuzzle]>
  [417] nteq .................................... <S <> pMenu[currPuzzle]>
  [418] jmpifz [436] ............................ if S <> pMenu[currPuzzle] then
  [421] getglobal 34 ............................ <pMenu>
  [423] getglobal 24 ............................ <currPuzzle>
  [425] getlocal 1 .............................. <S>
  [427] pusharglistnoret 3 ...................... <pMenu, currPuzzle, S>
  [429] objcall 35 .............................. pMenu[currPuzzle] = S
  [431] pusharglistnoret 0 ...................... <>
  [433] extcall 376 ............................. menu_Set_Items()
  [436] jmp [1447]
  [439] peek 0
  [441] pushint8 20 ............................. <20>
  [443] eq
  [444] jmpifz [505] ............................ (case) 20:
  [447] pushcons 4 .............................. <"gStat">
  [449] pushint8 1 .............................. <1>
  [451] pusharglist 2 ........................... <"gStat", 1>
  [453] extcall 43 .............................. <misc_GetFlash("gStat", 1)>
  [455] setlocal 2 .............................. N = misc_GetFlash("gStat", 1)
  [457] getlocal 2 .............................. <N>
  [459] pusharglistnoret 1 ...................... <N>
  [461] extcall 271 ............................. _Set_Game_Menu_Status(N)
  [464] pushcons 5 .............................. <"Menu">
  [466] getglobal 93 ............................ <pStat>
  [468] getglobal 21 ............................ <cGameMenus>
  [470] pusharglist 2 ........................... <pStat, cGameMenus>
  [472] objcall 17 .............................. <pStat[cGameMenus]>
  [474] joinpadstr .............................. <"Menu" && pStat[cGameMenus]>
  [475] pusharglistnoret 1 ...................... <"Menu" && pStat[cGameMenus]>
  [477] extcall 174 ............................. _PUT("Menu" && pStat[cGameMenus])
  [479] pusharglistnoret 0 ...................... <>
  [481] extcall 373 ............................. menu_Click_Snd()
  [484] gettoplevelprop 14 ...................... <_movie>
  [486] pushint8 9 .............................. <9>
  [488] pushint8 1 .............................. <1>
  [490] pushint8 20 ............................. <20>
  [492] pushzero ................................ <0>
  [493] pusharglistnoret 5 ...................... <_movie, 9, 1, 20, 0>
  [495] objcall 15 .............................. _movie.puppetTransition(9, 1, 20, 0)
  [497] pusharglistnoret 0 ...................... <>
  [499] extcall 377 ............................. comp_Main_Launch()
  [502] jmp [1447]
  [505] peek 0
  [507] pushint8 21 ............................. <21>
  [509] eq
  [510] jmpifz [527] ............................ (case) 21:
  [513] pushint8 1 .............................. <1>
  [515] pusharglist 1 ........................... <1>
  [517] localcall 1 ............................. <extractRequest(1)>
  [519] pusharglistnoret 1 ...................... <extractRequest(1)>
  [521] extcall 378 ............................. comp_Next_Column(extractRequest(1))
  [524] jmp [1447]
  [527] peek 0
  [529] pushint8 22 ............................. <22>
  [531] eq
  [532] jmpifz [565] ............................ (case) 22:
  [535] getglobal 93 ............................ <pStat>
  [537] getglobal 21 ............................ <cGameMenus>
  [539] pusharglist 2 ........................... <pStat, cGameMenus>
  [541] objcall 17 .............................. <pStat[cGameMenus]>
  [543] pushint8 94 ............................. <94>
  [545] lt ...................................... <pStat[cGameMenus] < 94>
  [546] jmpifz [557] ............................ if pStat[cGameMenus] < 94 then / else
  [549] pusharglistnoret 0 ...................... <>
  [551] extcall 379 ............................. comp_Splash_Launch()
  [554] jmp [562]
  [557] pusharglistnoret 0 ...................... <>
  [559] extcall 380 ............................. comp_Drown_Launch()
  [562] jmp [1447]
  [565] peek 0
  [567] pushint8 23 ............................. <23>
  [569] eq
  [570] jmpifz [581] ............................ (case) 23:
  [573] pusharglistnoret 0 ...................... <>
  [575] extcall 380 ............................. comp_Drown_Launch()
  [578] jmp [1447]
  [581] peek 0
  [583] pushint8 24 ............................. <24>
  [585] eq
  [586] jmpifz [612] ............................ (case) 24:
  [589] gettoplevelprop 14 ...................... <_movie>
  [591] pushint8 9 .............................. <9>
  [593] pushint8 1 .............................. <1>
  [595] pushint8 20 ............................. <20>
  [597] pushzero ................................ <0>
  [598] pusharglistnoret 5 ...................... <_movie, 9, 1, 20, 0>
  [600] objcall 15 .............................. _movie.puppetTransition(9, 1, 20, 0)
  [602] getglobal 21 ............................ <cGameMenus>
  [604] pushzero ................................ <0>
  [605] pusharglistnoret 2 ...................... <cGameMenus, 0>
  [607] extcall 20 .............................. initLaunch(cGameMenus, 0)
  [609] jmp [1447]
  [612] peek 0
  [614] pushint8 25 ............................. <25>
  [616] eq
  [617] jmpifz [643] ............................ (case) 25:
  [620] gettoplevelprop 14 ...................... <_movie>
  [622] pushint8 9 .............................. <9>
  [624] pushint8 1 .............................. <1>
  [626] pushint8 20 ............................. <20>
  [628] pushzero ................................ <0>
  [629] pusharglistnoret 5 ...................... <_movie, 9, 1, 20, 0>
  [631] objcall 15 .............................. _movie.puppetTransition(9, 1, 20, 0)
  [633] getglobal 21 ............................ <cGameMenus>
  [635] pushzero ................................ <0>
  [636] pusharglistnoret 2 ...................... <cGameMenus, 0>
  [638] extcall 20 .............................. initLaunch(cGameMenus, 0)
  [640] jmp [1447]
  [643] peek 0
  [645] pushint8 30 ............................. <30>
  [647] eq
  [648] jmpifz [662] ............................ (case) 30:
  [651] getglobal 25 ............................ <cFinale>
  [653] pushint8 1 .............................. <1>
  [655] pusharglistnoret 2 ...................... <cFinale, 1>
  [657] extcall 20 .............................. initLaunch(cFinale, 1)
  [659] jmp [1447]
  [662] peek 0
  [664] pushint8 31 ............................. <31>
  [666] eq
  [667] jmpifz [677] ............................ (case) 31:
  [670] pusharglistnoret 0 ...................... <>
  [672] extcall 0 ............................... fin_Play()
  [674] jmp [1447]
  [677] peek 0
  [679] pushint8 88 ............................. <88>
  [681] eq
  [682] jmpifz [700] ............................ (case) 88:
  [685] getglobal 21 ............................ <cGameMenus>
  [687] pushint8 1 .............................. <1>
  [689] pusharglistnoret 2 ...................... <cGameMenus, 1>
  [691] extcall 20 .............................. initLaunch(cGameMenus, 1)
  [693] pushint8 9 .............................. <9>
  [695] setglobal 19 ............................ pTransition = 9
  [697] jmp [1447]
  [700] peek 0
  [702] pushint8 89 ............................. <89>
  [704] eq
  [705] jmpifz [727] ............................ (case) 89:
  [708] pushint8 69 ............................. <69>
  [710] pusharglistnoret 1 ...................... <69>
  [712] extcall 271 ............................. _Set_Game_Menu_Status(69)
  [715] getglobal 261 ........................... <cHighPriestess>
  [718] pushint8 1 .............................. <1>
  [720] pusharglistnoret 2 ...................... <cHighPriestess, 1>
  [722] extcall 20 .............................. initLaunch(cHighPriestess, 1)
  [724] jmp [1447]
  [727] peek 0
  [729] pushint8 90 ............................. <90>
  [731] eq
  [732] jmpifz [747] ............................ (case) 90:
  [735] getglobal 381 ........................... <cEndHP>
  [738] pushint8 1 .............................. <1>
  [740] pusharglistnoret 2 ...................... <cEndHP, 1>
  [742] extcall 20 .............................. initLaunch(cEndHP, 1)
  [744] jmp [1447]
  [747] peek 0
  [749] pushint8 91 ............................. <91>
  [751] eq
  [752] jmpifz [777] ............................ (case) 91:
  [755] getglobal 93 ............................ <pStat>
  [757] pushint8 3 .............................. <3>
  [759] pushint16 190 ........................... <190>
  [762] pusharglistnoret 3 ...................... <pStat, 3, 190>
  [764] objcall 35 .............................. pStat[3] = 190
  [766] pushint8 3 .............................. <3>
  [768] pushint8 1 .............................. <1>
  [770] pusharglistnoret 2 ...................... <3, 1>
  [772] extcall 20 .............................. initLaunch(3, 1)
  [774] jmp [1447]
  [777] peek 0
  [779] pushint8 95 ............................. <95>
  [781] eq
  [782] jmpifz [832] ............................ (case) 95:
  [785] pusharglistnoret 0 ...................... <>
  [787] extcall 373 ............................. menu_Click_Snd()
  [790] pushint8 1 .............................. <1>
  [792] pusharglist 1 ........................... <1>
  [794] localcall 1 ............................. <extractRequest(1)>
  [796] setlocal 2 .............................. N = extractRequest(1)
  [798] getglobal 204 ........................... <csWagerTarot>
  [800] getlocal 2 .............................. <N>
  [802] getglobal 327 ........................... <csTarot>
  [805] getlocal 2 .............................. <N>
  [807] pusharglist 2 ........................... <csTarot, N>
  [809] objcall 17 .............................. <csTarot[N]>
  [811] pusharglistnoret 3 ...................... <csWagerTarot, N, csTarot[N]>
  [813] objcall 35 .............................. csWagerTarot[N] = csTarot[N]
  [815] getglobal 204 ........................... <csWagerTarot>
  [817] getlocal 2 .............................. <N>
  [819] pusharglist 2 ........................... <csWagerTarot, N>
  [821] objcall 17 .............................. <csWagerTarot[N]>
  [823] pushint8 1 .............................. <1>
  [825] pusharglistnoret 2 ...................... <csWagerTarot[N], 1>
  [827] extcall 20 .............................. initLaunch(csWagerTarot[N], 1)
  [829] jmp [1447]
  [832] peek 0
  [834] pushint8 96 ............................. <96>
  [836] eq
  [837] jmpifz [891] ............................ (case) 96:
  [840] pusharglistnoret 0 ...................... <>
  [842] extcall 373 ............................. menu_Click_Snd()
  [845] pusharglistnoret 0 ...................... <>
  [847] extcall 272 ............................. _Update_Solved_Tarot()
  [850] pushint8 1 .............................. <1>
  [852] pusharglist 1 ........................... <1>
  [854] localcall 1 ............................. <extractRequest(1)>
  [856] setlocal 2 .............................. N = extractRequest(1)
  [858] getglobal 204 ........................... <csWagerTarot>
  [860] getlocal 2 .............................. <N>
  [862] getglobal 217 ........................... <csWager>
  [864] getlocal 2 .............................. <N>
  [866] pusharglist 2 ........................... <csWager, N>
  [868] objcall 17 .............................. <csWager[N]>
  [870] pusharglistnoret 3 ...................... <csWagerTarot, N, csWager[N]>
  [872] objcall 35 .............................. csWagerTarot[N] = csWager[N]
  [874] getglobal 204 ........................... <csWagerTarot>
  [876] getlocal 2 .............................. <N>
  [878] pusharglist 2 ........................... <csWagerTarot, N>
  [880] objcall 17 .............................. <csWagerTarot[N]>
  [882] pushint8 1 .............................. <1>
  [884] pusharglistnoret 2 ...................... <csWagerTarot[N], 1>
  [886] extcall 20 .............................. initLaunch(csWagerTarot[N], 1)
  [888] jmp [1447]
  [891] peek 0
  [893] pushint8 97 ............................. <97>
  [895] eq
  [896] jmpifz [902] ............................ (case) 97:
  [899] jmp [1447]
  [902] peek 0
  [904] pushint8 98 ............................. <98>
  [906] eq
  [907] jmpifz [927] ............................ (case) 98:
  [910] pusharglistnoret 0 ...................... <>
  [912] extcall 373 ............................. menu_Click_Snd()
  [915] getglobal 291 ........................... <cMoonsPuzzles>
  [918] pushint8 1 .............................. <1>
  [920] pusharglistnoret 2 ...................... <cMoonsPuzzles, 1>
  [922] extcall 20 .............................. initLaunch(cMoonsPuzzles, 1)
  [924] jmp [1447]
  [927] peek 0
  [929] pushint8 99 ............................. <99>
  [931] eq
  [932] jmpifz [946] ............................ (case) 99:
  [935] getglobal 21 ............................ <cGameMenus>
  [937] pushint8 1 .............................. <1>
  [939] pusharglistnoret 2 ...................... <cGameMenus, 1>
  [941] extcall 20 .............................. initLaunch(cGameMenus, 1)
  [943] jmp [1447]
  [946] peek 0
  [948] getglobal 202 ........................... <cTokens>
  [950] eq
  [951] jmpifz [1416] ........................... (case) cTokens:
  [954] pushint8 1 .............................. <1>
  [956] pusharglist 1 ........................... <1>
  [958] localcall 1 ............................. <extractRequest(1)>
  [960] peek 0 .................................. case extractRequest(1) of
  [962] pushint8 1 .............................. <1>
  [964] eq
  [965] jmpifz [1036] ........................... (case) 1:
  [968] pushint8 1 .............................. <1>
  [970] pusharglist 1 ........................... <1>
  [972] localcall 1 ............................. <extractRequest(1)>
  [974] setlocal 3 .............................. n1 = extractRequest(1)
  [976] pushint8 1 .............................. <1>
  [978] pusharglist 1 ........................... <1>
  [980] localcall 1 ............................. <extractRequest(1)>
  [982] setlocal 4 .............................. n2 = extractRequest(1)
  [984] getglobal 382 ........................... <status_First_Launch>
  [987] pushzero ................................ <0>
  [988] eq ...................................... <status_First_Launch = 0>
  [989] jmpifz [1021] ........................... if status_First_Launch = 0 then / else
  [992] getlocal 4 .............................. <n2>
  [994] pushzero ................................ <0>
  [995] eq ...................................... <n2 = 0>
  [996] jmpifz [1010] ........................... if n2 = 0 then / else
  [999] getlocal 3 .............................. <n1>
  [1001] pushint8 1 ............................. <1>
  [1003] pusharglistnoret 2 ..................... <n1, 1>
  [1005] extcall 169 ............................ launchGame(n1, 1)
  [1007] jmp [1018]
  [1010] getglobal 328 .......................... <lastPuzzle>
  [1013] pushzero ............................... <0>
  [1014] pusharglistnoret 2 ..................... <lastPuzzle, 0>
  [1016] extcall 20 ............................. initLaunch(lastPuzzle, 0)
  [1018] jmp [1033]
  [1021] pushzero ............................... <0>
  [1022] setglobal 382 .......................... status_First_Launch = 0
  [1025] getlocal 3 ............................. <n1>
  [1027] pushint8 1 ............................. <1>
  [1029] pusharglistnoret 2 ..................... <n1, 1>
  [1031] extcall 169 ............................ launchGame(n1, 1)
  [1033] jmp [1411]
  [1036] peek 0
  [1038] pushint8 2 ............................. <2>
  [1040] eq
  [1041] jmpifz [1047] .......................... (case) 2:
  [1044] jmp [1411]
  [1047] peek 0
  [1049] pushint8 3 ............................. <3>
  [1051] eq
  [1052] jmpifz [1092] .......................... (case) 3:
  [1055] pushint8 1 ............................. <1>
  [1057] pusharglist 1 .......................... <1>
  [1059] localcall 1 ............................ <extractRequest(1)>
  [1061] setlocal 3 ............................. n1 = extractRequest(1)
  [1063] pushint8 1 ............................. <1>
  [1065] pusharglist 1 .......................... <1>
  [1067] localcall 1 ............................ <extractRequest(1)>
  [1069] setlocal 4 ............................. n2 = extractRequest(1)
  [1071] getlocal 3 ............................. <n1>
  [1073] setglobal 168 .......................... currGame = n1
  [1075] pushzero ............................... <0>
  [1076] pushcons 6 ............................. <"YES">
  [1078] pusharglistnoret 2 ..................... <0, "YES">
  [1080] extcall 383 ............................ token_Save(0, "YES")
  [1083] getlocal 4 ............................. <n2>
  [1085] pusharglistnoret 1 ..................... <n2>
  [1087] extcall 180 ............................ putLastGamePref(n2)
  [1089] jmp [1411]
  [1092] peek 0
  [1094] pushint8 4 ............................. <4>
  [1096] eq
  [1097] jmpifz [1157] .......................... (case) 4:
  [1100] pushint8 1 ............................. <1>
  [1102] pusharglist 1 .......................... <1>
  [1104] localcall 1 ............................ <extractRequest(1)>
  [1106] setlocal 3 ............................. n1 = extractRequest(1)
  [1108] pushint8 1 ............................. <1>
  [1110] pusharglist 1 .......................... <1>
  [1112] localcall 1 ............................ <extractRequest(1)>
  [1114] setlocal 4 ............................. n2 = extractRequest(1)
  [1116] getglobal 201 .......................... <token3>
  [1118] getglobal 171 .......................... <cRevGameNum>
  [1120] pusharglist 2 .......................... <token3, cRevGameNum>
  [1122] objcall 17 ............................. <token3[cRevGameNum]>
  [1124] pushint8 1 ............................. <1>
  [1126] eq ..................................... <token3[cRevGameNum] = 1>
  [1127] jmpifz [1140] .......................... if token3[cRevGameNum] = 1 then
  [1130] getglobal 200 .......................... <token2>
  [1132] getglobal 171 .......................... <cRevGameNum>
  [1134] pushcons 7 ............................. <"Your fortune awaits.">
  [1136] pusharglistnoret 3 ..................... <token2, cRevGameNum, "Your fortune awaits.">
  [1138] objcall 35 ............................. token2[cRevGameNum] = "Your fortune awaits."
  [1140] getlocal 3 ............................. <n1>
  [1142] getglobal 171 .......................... <cRevGameNum>
  [1144] pusharglistnoret 2 ..................... <n1, cRevGameNum>
  [1146] extcall 172 ............................ copyTokens(n1, cRevGameNum)
  [1148] getlocal 4 ............................. <n2>
  [1150] pusharglistnoret 1 ..................... <n2>
  [1152] extcall 180 ............................ putLastGamePref(n2)
  [1154] jmp [1411]
  [1157] peek 0
  [1159] pushint8 5 ............................. <5>
  [1161] eq
  [1162] jmpifz [1178] .......................... (case) 5:
  [1165] pushint8 1 ............................. <1>
  [1167] pusharglist 1 .......................... <1>
  [1169] localcall 1 ............................ <extractRequest(1)>
  [1171] pusharglistnoret 1 ..................... <extractRequest(1)>
  [1173] extcall 112 ............................ getRevertFoolFile(extractRequest(1))
  [1175] jmp [1411]
  [1178] peek 0
  [1180] pushint8 6 ............................. <6>
  [1182] eq
  [1183] jmpifz [1199] .......................... (case) 6:
  [1186] pushint8 1 ............................. <1>
  [1188] pusharglist 1 .......................... <1>
  [1190] localcall 1 ............................ <extractRequest(1)>
  [1192] pusharglistnoret 1 ..................... <extractRequest(1)>
  [1194] extcall 119 ............................ eraseFoolFile(extractRequest(1))
  [1196] jmp [1411]
  [1199] peek 0
  [1201] pushint8 7 ............................. <7>
  [1203] eq
  [1204] jmpifz [1214] .......................... (case) 7:
  [1207] pusharglistnoret 0 ..................... <>
  [1209] extcall 120 ............................ eraseAllFoolFiles()
  [1211] jmp [1411]
  [1214] peek 0
  [1216] pushint8 8 ............................. <8>
  [1218] eq
  [1219] jmpifz [1234] .......................... (case) 8:
  [1222] pushint8 1 ............................. <1>
  [1224] pushcons 8 ............................. <"Save/Quit">
  [1226] pusharglistnoret 2 ..................... <1, "Save/Quit">
  [1228] extcall 383 ............................ token_Save(1, "Save/Quit")
  [1231] jmp [1411]
  [1234] peek 0
  [1236] pushint8 9 ............................. <9>
  [1238] eq
  [1239] jmpifz [1250] .......................... (case) 9:
  [1242] pusharglistnoret 0 ..................... <>
  [1244] extcall 384 ............................ update_Double_Secret()
  [1247] jmp [1411]
  [1250] peek 0
  [1252] pushint8 10 ............................ <10>
  [1254] eq
  [1255] jmpifz [1269] .......................... (case) 10:
  [1258] getglobal 328 .......................... <lastPuzzle>
  [1261] pushzero ............................... <0>
  [1262] pusharglistnoret 2 ..................... <lastPuzzle, 0>
  [1264] extcall 20 ............................. initLaunch(lastPuzzle, 0)
  [1266] jmp [1411]
  [1269] peek 0
  [1271] pushint8 11 ............................ <11>
  [1273] eq
  [1274] jmpifz [1288] .......................... (case) 11:
  [1277] pushzero ............................... <0>
  [1278] pushcons 9 ............................. <"Save">
  [1280] pusharglistnoret 2 ..................... <0, "Save">
  [1282] extcall 383 ............................ token_Save(0, "Save")
  [1285] jmp [1411]
  [1288] peek 0
  [1290] pushint8 12 ............................ <12>
  [1292] eq
  [1293] jmpifz [1299] .......................... (case) 12:
  [1296] jmp [1411]
  [1299] peek 0
  [1301] pushint8 13 ............................ <13>
  [1303] eq
  [1304] jmpifz [1310] .......................... (case) 13:
  [1307] jmp [1411]
  [1310] peek 0
  [1312] pushint8 14 ............................ <14>
  [1314] eq
  [1315] jmpifz [1321] .......................... (case) 14:
  [1318] jmp [1411]
  [1321] peek 0
  [1323] pushint8 15 ............................ <15>
  [1325] eq
  [1326] jmpifz [1341] .......................... (case) 15:
  [1329] pushcons 10 ............................ <"http://www.thefoolandhismoney.com/07-Hints/index.htm">
  [1331] pushcons 11 ............................ <"_new">
  [1333] pusharglistnoret 2 ..................... <"http://www.thefoolandhismoney.com/07-Hints/index.htm", "_new">
  [1335] extcall 385 ............................ gotoNetPage("http://www.thefoolandhismoney.com/07-Hints/index.htm", "_new")
  [1338] jmp [1411]
  [1341] peek 0
  [1343] pushint8 16 ............................ <16>
  [1345] eq
  [1346] jmpifz [1382] .......................... (case) 16:
  [1349] getglobal 24 ........................... <currPuzzle>
  [1351] setglobal 386 .......................... tokens_LastPuzzle = currPuzzle
  [1354] pushint8 1 ............................. <1>
  [1356] pusharglist 1 .......................... <1>
  [1358] localcall 1 ............................ <extractRequest(1)>
  [1360] setglobal 387 .......................... tokens_CurrentGame = extractRequest(1)
  [1363] pushint8 1 ............................. <1>
  [1365] pusharglist 1 .......................... <1>
  [1367] localcall 1 ............................ <extractRequest(1)>
  [1369] setglobal 388 .......................... tokens_NeedToSave = extractRequest(1)
  [1372] getglobal 247 .......................... <cHelpTokens>
  [1374] pushzero ............................... <0>
  [1375] pusharglistnoret 2 ..................... <cHelpTokens, 0>
  [1377] extcall 20 ............................. initLaunch(cHelpTokens, 0)
  [1379] jmp [1411]
  [1382] peek 0
  [1384] pushint8 17 ............................ <17>
  [1386] eq
  [1387] jmpifz [1411] .......................... (case) 17:
  [1390] getglobal 93 ........................... <pStat>
  [1392] getglobal 247 .......................... <cHelpTokens>
  [1394] pushzero ............................... <0>
  [1395] pusharglistnoret 3 ..................... <pStat, cHelpTokens, 0>
  [1397] objcall 35 ............................. pStat[cHelpTokens] = 0
  [1399] pusharglistnoret 0 ..................... <>
  [1401] extcall 389 ............................ token_RestoreSaved()
  [1404] getglobal 202 .......................... <cTokens>
  [1406] pushzero ............................... <0>
  [1407] pusharglistnoret 2 ..................... <cTokens, 0>
  [1409] extcall 20 ............................. initLaunch(cTokens, 0)
  [1411] pop 1 .................................. end case
  [1413] jmp [1447] ............................. (case) otherwise:
  [1416] pushint8 1 ............................. <1>
  [1418] setlocal 5
  [1420] getlocal 5
  [1422] pushint8 17 ............................ <17>
  [1424] lteq
  [1425] jmpifz [1447] .......................... repeat with x = 1 to 17
  [1428] pushcons 12 ............................ <"NO">
  [1430] getglobal 374 .......................... <theRequest>
  [1433] joinpadstr ............................. <"NO" && theRequest>
  [1434] pusharglistnoret 1 ..................... <"NO" && theRequest>
  [1436] extcall 174 ............................ _PUT("NO" && theRequest)
  [1438] pushint8 1
  [1440] getlocal 5
  [1442] add
  [1443] setlocal 5
  [1445] endrepeat [1420]
  [1447] pop 1 .................................. end case
  [1449] ret
end
